CHANGES.txt
LICENSE.txt
MANIFEST.in
README.txt
setup.py
objpool/__init__.py
objpool/http.py
objpool/version.py
objpool.egg-info/PKG-INFO
objpool.egg-info/SOURCES.txt
objpool.egg-info/dependency_links.txt
objpool.egg-info/top_level.txt