Metadata-Version: 1.0
Name: objpool
Version: 0.3
Summary: An object pooling library
Home-page: https://github.com/grnet/objpool
Author: Synnefo development team
Author-email: synnefo-devel@googlegroups.com
License: LICENSE.txt
Platform: UNKNOWN
